{"lists":[{"id":4,"name":"Alex","phone":"89725122321","userIdOwner":1},{"id":5,"name":"Liza","phone":"89723122321","userIdOwner":1},{"id":6,"name":"John","phone":"89722322321","userIdOwner":1},{"id":7,"name":"Olga","phone":"89722322334","userIdOwner":2},{"id":8,"name":"Igor","phone":"89774548574","userIdOwner":2},{"id":9,"name":"Max","phone":"89885251552","userIdOwner":4},{"id":10,"name":"Ira","phone":"891654585254","userIdOwner":4},{"id":11,"name":"Sasha","phone":"89841542525","userIdOwner":5}]}